gfram/__init__.py
gfram/version.py
gfram/api/__init__.py
gfram/api/simple_recognizer.py
gfram/cloud/__init__.py
gfram/cloud/model_loader.py
gfram/cloud/server_client.py
gfram/detectors/__init__.py
gfram/detectors/face_detector.py
gfram/evaluation/__init__.py
gfram/evaluation/benchmarks.py
gfram/evaluation/metrics.py
gfram/geometry/__init__.py
gfram/geometry/features.py
gfram/geometry/landmarks.py
gfram/geometry/moments.py
gfram/geometry/symmetry.py
gfram/geometry/topology.py
gfram/geometry/triangulation.py
gfram/matching/__init__.py
gfram/matching/index.py
gfram/models/__init__.py
gfram/models/geometric_transformer.py
gfram/models/losses.py
gfram/training/__init__.py
gfram/training/incremental.py
gfram/training/trainer.py
gfram/utils/__init__.py
gfram/utils/config.py
gfram/utils/io.py
gfram/utils/visualization.py
gfram-3.0.0.dist-info/licenses/LICENSE
gfram-3.0.0.dist-info/METADATA
gfram-3.0.0.dist-info/WHEEL
gfram-3.0.0.dist-info/top_level.txt
gfram-3.0.0.dist-info/RECORD
