Metadata-Version: 2.4
Name: gfram
Version: 3.0.0
Summary: Professional geometric face recognition library with AI-powered matching
Home-page: https://github.com/feruza-42h/gfram
Author: Ortiqova F.S.
Author-email: "Ortiqova F.S" <feruzaortiqova42@gmail.com>
License-Expression: MIT
Project-URL: Homepage, https://github.com/feruza-42h/gfram
Project-URL: Documentation, https://gfram.readthedocs.io
Project-URL: Repository, https://github.com/feruza-42h/gfram
Project-URL: Bug Tracker, https://github.com/feruza-42h/gfram/issues
Keywords: face-recognition,geometric-methods,computer-vision,biometrics,machine-learning,deep-learning,transformer,graph-neural-network
Classifier: Development Status :: 4 - Beta
Classifier: Intended Audience :: Developers
Classifier: Intended Audience :: Science/Research
Classifier: Programming Language :: Python :: 3
Classifier: Programming Language :: Python :: 3.8
Classifier: Programming Language :: Python :: 3.9
Classifier: Programming Language :: Python :: 3.10
Classifier: Programming Language :: Python :: 3.11
Classifier: Topic :: Scientific/Engineering :: Artificial Intelligence
Classifier: Topic :: Scientific/Engineering :: Image Recognition
Requires-Python: >=3.8
License-File: LICENSE
Requires-Dist: numpy>=1.21.0
Requires-Dist: scipy>=1.7.0
Requires-Dist: opencv-python>=4.5.0
Requires-Dist: mediapipe>=0.10.0
Requires-Dist: scikit-learn>=1.0.0
Requires-Dist: torch>=2.0.0
Requires-Dist: faiss-cpu>=1.7.0
Requires-Dist: tqdm>=4.62.0
Requires-Dist: pyyaml>=6.0
Requires-Dist: pillow>=9.0.0
Provides-Extra: dev
Requires-Dist: pytest>=7.0.0; extra == "dev"
Requires-Dist: pytest-cov>=3.0.0; extra == "dev"
Requires-Dist: black>=22.0.0; extra == "dev"
Requires-Dist: flake8>=4.0.0; extra == "dev"
Requires-Dist: mypy>=0.950; extra == "dev"
Requires-Dist: sphinx>=4.5.0; extra == "dev"
Provides-Extra: gpu
Requires-Dist: faiss-gpu>=1.7.0; extra == "gpu"
Provides-Extra: geometric
Requires-Dist: torch-geometric>=2.3.0; extra == "geometric"
Requires-Dist: torch-scatter>=2.1.0; extra == "geometric"
Requires-Dist: torch-sparse>=0.6.0; extra == "geometric"
Provides-Extra: all
Requires-Dist: gfram[dev,geometric,gpu]; extra == "all"
Dynamic: author
Dynamic: home-page
Dynamic: license-file
Dynamic: requires-python
